setup.py
mxn/__init__.py
mxn/constitutive_law.py
mxn/cross_section.py
mxn/cross_section_component.py
mxn/cross_section_state.py
mxn/ecb_calib.py
mxn/mxn_class_extension.py
mxn/mxn_class_extension_handler.py
mxn/mxn_diagram.py
mxn/mxn_tree_node.py
mxn.egg-info/PKG-INFO
mxn.egg-info/SOURCES.txt
mxn.egg-info/dependency_links.txt
mxn.egg-info/entry_points.txt
mxn.egg-info/requires.txt
mxn.egg-info/top_level.txt
mxn/docs/__init__.py
mxn/docs/conf.py
mxn/docs/ecb_classes.rst
mxn/docs/front.rst
mxn/docs/gen_docs.py
mxn/docs/index.rst
mxn/docs/intro.rst
mxn/material_types/__init__.py
mxn/material_types/material_type_base.py
mxn/material_types/material_type_handler.py
mxn/material_types/material_type_matrix_mixture.py
mxn/material_types/material_type_reinf_bar.py
mxn/material_types/material_type_reinf_fabric.py
mxn/matresdev/__init__.py
mxn/matresdev/db/__init__.py
mxn/matresdev/db/exdb/TT-csv-dat-file-generator.py
mxn/matresdev/db/exdb/TT-csv-file-generator_W20_hre.py
mxn/matresdev/db/exdb/__init__.py
mxn/matresdev/db/exdb/__test__.py
mxn/matresdev/db/exdb/ex_run.py
mxn/matresdev/db/exdb/ex_run_table.py
mxn/matresdev/db/exdb/ex_run_view.py
mxn/matresdev/db/exdb/ex_treatment.py
mxn/matresdev/db/exdb/ex_type.py
mxn/matresdev/db/exdb/ex_type_data_analysis_methods.py
mxn/matresdev/db/exdb/ex_utils.py
mxn/matresdev/db/exdb/i_ex_run.py
mxn/matresdev/db/exdb/i_ex_type.py
mxn/matresdev/db/exdb/loadtxt_bending.py
mxn/matresdev/db/exdb/loadtxt_novalue.py
mxn/matresdev/db/exdb/test.py
mxn/matresdev/db/exdb/unit_converter.py
mxn/matresdev/db/matdb/__init__.py
mxn/matresdev/db/matdb/trc/__init__.py
mxn/matresdev/db/matdb/trc/ccs_unit_cell.py
mxn/matresdev/db/matdb/trc/composite_cross_section.py
mxn/matresdev/db/matdb/trc/concrete_mixture.py
mxn/matresdev/db/matdb/trc/fabric_layout.py
mxn/matresdev/db/matdb/trc/fabric_layup.py
mxn/matresdev/db/plugins/__init__.py
mxn/matresdev/db/plugins/promod_plugin.py
mxn/matresdev/db/plugins/promod_service.py
mxn/matresdev/db/plugins/promod_ui_plugin.py
mxn/matresdev/db/simdb/__init__.py
mxn/matresdev/db/simdb/sftp_server.py
mxn/matresdev/db/simdb/simdb.py
mxn/matresdev/db/simdb/simdb_add_trait.py
