Metadata-Version: 1.1
Name: mxn
Version: 0.0.5a15
Summary: Tool for determination of interaction envelope of a composite cross-section.
Home-page: http://packages.python.org/mxn
Author: Rostislav Chudoba, Vladimir Vancik
Author-email: rostislav.chudoba@rwth-aachen.de
License: BSD
Keywords: moment-normal force interaction
Platform: UNKNOWN
Classifier: Development Status :: 3 - Alpha
Classifier: Topic :: Utilities
Classifier: License :: OSI Approved :: BSD License
